pddoc/__init__.py
pddoc/cairofont.py
pddoc/cairopainter.py
pddoc/categoryparser.py
pddoc/colorformatter.py
pddoc/docobject.py
pddoc/docobjectvisitor.py
pddoc/htmldocvisitor.py
pddoc/idocobjectvisitor.py
pddoc/latexdocobjectvisitor.py
pddoc/layout.py
pddoc/library.py
pddoc/libraryparser.py
pddoc/parser.py
pddoc/pddocvisitor.py
pddoc/pddrawer.py
pddoc/pdlayout.py
pddoc/pdpage.py
pddoc/pdpainter.py
pddoc/sphinx_ext.py
pddoc/xletdocvisitor.py
pddoc/bin/__init__.py
pddoc/bin/format.py
pddoc/bin/pd_ascii2pd.py
pddoc/bin/pd_cat2pd.py
pddoc/bin/pd_doc2html.py
pddoc/bin/pd_doc2pd.py
pddoc/bin/pd_faust2gui.py
pddoc/bin/pd_lib2pd.py
pddoc/bin/pd_makelibrary.py
pddoc/bin/pd_obj2img.py
pddoc/bin/pd_pd2img.py
pddoc/pd/__init__.py
pddoc/pd/abstractvisitor.py
pddoc/pd/array.py
pddoc/pd/baseobject.py
pddoc/pd/bng.py
pddoc/pd/brectcalculator.py
pddoc/pd/canvas.py
pddoc/pd/comment.py
pddoc/pd/coregui.py
pddoc/pd/drawstyle.py
pddoc/pd/factory.py
pddoc/pd/floatatom.py
pddoc/pd/gcanvas.py
pddoc/pd/message.py
pddoc/pd/nbx.py
pddoc/pd/obj.py
pddoc/pd/objetcbrectvisitor.py
pddoc/pd/parser.py
pddoc/pd/pdexporter.py
pddoc/pd/radio.py
pddoc/pd/slider.py
pddoc/pd/symbolatom.py
pddoc/pd/toggle.py
pddoc/pd/vu.py
pddoc/pd/xletcalcdatabase.py
pddoc/pd/xletcalculator.py
pddoc/pd/xletdatabase.py
pddoc/pd/xletpatchlookup.py
pddoc/pd/xlettextdatabase.py
pddoc/pd/externals/__init__.py
pddoc/pd/externals/bsaylor/bsaylor.db
pddoc/pd/externals/ceammc/__init__.py
pddoc/pd/externals/ceammc/ui_aview.py
pddoc/pd/externals/ceammc/ui_bang.py
pddoc/pd/externals/ceammc/ui_base.py
pddoc/pd/externals/ceammc/ui_bpfunc.py
pddoc/pd/externals/ceammc/ui_display.py
pddoc/pd/externals/ceammc/ui_env.py
pddoc/pd/externals/ceammc/ui_keyboard.py
pddoc/pd/externals/ceammc/ui_knob.py
pddoc/pd/externals/ceammc/ui_link.py
pddoc/pd/externals/ceammc/ui_matrix.py
pddoc/pd/externals/ceammc/ui_meter.py
pddoc/pd/externals/ceammc/ui_preset.py
pddoc-0.5.4.dist-info/METADATA
pddoc-0.5.4.dist-info/RECORD
pddoc-0.5.4.dist-info/WHEEL
pddoc-0.5.4.dist-info/entry_points.txt
pddoc-0.5.4.dist-info/top_level.txt
