Metadata-Version: 2.1
Name: pddoc
Version: 0.5.4
Summary: PureData documentation tools
Home-page: https://github.com/uliss/pddoc
Author: Serge Poltavski
Author-email: serge.poltavski@gmail.com
License: GPLv3
Keywords: puredata documentation
Platform: UNKNOWN
Classifier: Development Status :: 4 - Beta
Classifier: Topic :: Software Development :: Documentation
Classifier: Topic :: Multimedia :: Sound/Audio
Classifier: Programming Language :: Python :: 3.3
Classifier: License :: OSI Approved :: GNU General Public License v3 or later (GPLv3+)
Requires-Dist: termcolor
Requires-Dist: colorama
Requires-Dist: six
Requires-Dist: mako
Requires-Dist: argparse
Requires-Dist: lxml
Requires-Dist: ply
Requires-Dist: docutils
Requires-Dist: sphinx
